mysql_mcp_server/__init__.py
mysql_mcp_server/server.py
mcp_mysql_server-1.0.2.dist-info/METADATA
mcp_mysql_server-1.0.2.dist-info/WHEEL
mcp_mysql_server-1.0.2.dist-info/entry_points.txt
mcp_mysql_server-1.0.2.dist-info/licenses/LICENSE
mcp_mysql_server-1.0.2.dist-info/RECORD
