Metadata-Version: 2.4
Name: mcp-mysql-server
Version: 1.0.2
Summary: A Model Context Protocol (MCP) server for MySQL databases with multi-database support and read-only mode. Enables AI assistants to securely query multiple MySQL databases.
Project-URL: Homepage, https://github.com/aahowe/mcp-mysql-server
Project-URL: Repository, https://github.com/aahowe/mcp-mysql-server
Project-URL: Documentation, https://github.com/aahowe/mcp-mysql-server#readme
Author-email: Hao Wang <wanghao@shopee.com>
License: MIT
License-File: LICENSE
Keywords: ai,claude,cursor,database,llm,mcp,model-context-protocol,mysql
Classifier: Development Status :: 4 - Beta
Classifier: Intended Audience :: Developers
Classifier: License :: OSI Approved :: MIT License
Classifier: Programming Language :: Python :: 3
Classifier: Programming Language :: Python :: 3.11
Classifier: Programming Language :: Python :: 3.12
Classifier: Topic :: Database
Classifier: Topic :: Software Development :: Libraries :: Python Modules
Requires-Python: >=3.11
Requires-Dist: mcp>=1.0.0
Requires-Dist: mysql-connector-python>=9.1.0
